pregress/__init__.py
pregress/utils.py
pregress/data/AirBnb.csv
pregress/data/Betas.csv
pregress/data/Charges.csv
pregress/data/Employment.csv
pregress/data/HR_retention.csv
pregress/data/HousePrices.csv
pregress/data/JobChanges.csv
pregress/data/LoanDefault.csv
pregress/data/MarketingToys.csv
pregress/data/Sales.csv
pregress/data/Top200.csv
pregress/data/Twitter.csv
pregress/data/Vacation.csv
pregress/data/Youtube.csv
pregress/data/__init__.py
pregress/data/salary_churn.csv
pregress/modeling/__init__.py
pregress/modeling/add_explicit_variable.py
pregress/modeling/apply_transformation.py
pregress/modeling/box_cox.py
pregress/modeling/bp_test.py
pregress/modeling/bsr.py
pregress/modeling/environment.py
pregress/modeling/extract_variable.py
pregress/modeling/fit.py
pregress/modeling/format_summary.py
pregress/modeling/handle_included_vars.py
pregress/modeling/handle_included_vars2.py
pregress/modeling/intervals.py
pregress/modeling/ncv_test.py
pregress/modeling/parse_formula.py
pregress/modeling/predict.py
pregress/modeling/print_anova_and_summary.py
pregress/modeling/print_anova_table.py
pregress/modeling/print_r_summary.py
pregress/modeling/print_stata_summary.py
pregress/modeling/shapiro_test.py
pregress/modeling/significance_code.py
pregress/modeling/step.py
pregress/modeling/summary.py
pregress/modeling/vif.py
pregress/modeling/xy_split.py
pregress/plots/__init__.py
pregress/plots/abline.py
pregress/plots/barplot.py
pregress/plots/boxplot.py
pregress/plots/hist.py
pregress/plots/hist_res.py
pregress/plots/hists.py
pregress/plots/plot_bsr.py
pregress/plots/plot_cook.py
pregress/plots/plot_cor.py
pregress/plots/plot_interval.py
pregress/plots/plot_intervals.py
pregress/plots/plot_qq.py
pregress/plots/plot_res.py
pregress/plots/plot_xy.py
pregress/plots/plots.py
pregress-1.0.9.dist-info/LICENSE
pregress-1.0.9.dist-info/METADATA
pregress-1.0.9.dist-info/WHEEL
pregress-1.0.9.dist-info/top_level.txt
pregress-1.0.9.dist-info/RECORD
