Metadata-Version: 2.1
Name: pregress
Version: 1.0.9
Summary: Python Regression Analysis.
Home-page: https://github.com/danmcgib/pregress
Author: Daniel McGibney
Author-email: dmcgibney@bus.miami.edu
Classifier: Programming Language :: Python :: 3
Classifier: License :: OSI Approved :: MIT License
Classifier: Operating System :: OS Independent
Requires-Python: >=3.6
License-File: LICENSE
Requires-Dist: matplotlib
Requires-Dist: pandas
Requires-Dist: numpy
Requires-Dist: statsmodels
Requires-Dist: seaborn
Requires-Dist: scikit-learn
Requires-Dist: scipy
